zgrobot/__init__.py
zgrobot/client.py
zgrobot/config.py
zgrobot/exceptions.py
zgrobot/logger.py
zgrobot/parser.py
zgrobot/pay.py
zgrobot/replies.py
zgrobot/robot.py
zgrobot/testing.py
zgrobot/utils.py
zgrobot/contrib/__init__.py
zgrobot/contrib/bottle.py
zgrobot/contrib/django.py
zgrobot/contrib/error.html
zgrobot/contrib/fastapi.py
zgrobot/contrib/flask.py
zgrobot/contrib/tornado.py
zgrobot/crypto/__init__.py
zgrobot/crypto/exceptions.py
zgrobot/crypto/pkcs7.py
zgrobot/messages/__init__.py
zgrobot/messages/base.py
zgrobot/messages/entries.py
zgrobot/messages/events.py
zgrobot/messages/messages.py
zgrobot/session/__init__.py
zgrobot/session/filestorage.py
zgrobot/session/mongodbstorage.py
zgrobot/session/mysqlstorage.py
zgrobot/session/postgresqlstorage.py
zgrobot/session/redisstorage.py
zgrobot/session/saekvstorage.py
zgrobot/session/sqlitestorage.py
zgrobot-2.0.5.dist-info/LICENSE
zgrobot-2.0.5.dist-info/METADATA
zgrobot-2.0.5.dist-info/WHEEL
zgrobot-2.0.5.dist-info/top_level.txt
zgrobot-2.0.5.dist-info/RECORD
