Metadata-Version: 2.1
Name: zgrobot
Version: 2.0.5
Summary: ZgRoBot: writing WeChat Offical Account Robots with fun
Home-page: https://github.com/pylover7/ZgRobot
Author: pylover
Author-email: shuoshuoyun@foxmail.com
License: MIT License
Project-URL: Documentation, https://zgrobot.readthedocs.io/zh/stable/
Project-URL: Source, https://github.com/pylover7/ZgRobot
Project-URL: Tracker, https://github.com/pylover7/ZgRobot/issues
Keywords: wechat weixin zgrobot
Classifier: Development Status :: 4 - Beta
Classifier: License :: OSI Approved :: MIT License
Classifier: Operating System :: MacOS
Classifier: Operating System :: POSIX
Classifier: Operating System :: POSIX :: Linux
Classifier: Programming Language :: Python
Classifier: Programming Language :: Python :: 3.7
Classifier: Programming Language :: Python :: 3.8
Classifier: Programming Language :: Python :: 3.9
Classifier: Programming Language :: Python :: Implementation :: CPython
Classifier: Intended Audience :: Developers
Classifier: Topic :: Software Development :: Libraries
Classifier: Topic :: Software Development :: Libraries :: Python Modules
Classifier: Topic :: Utilities
Requires-Python: >=3
License-File: LICENSE
Requires-Dist: bottle
Requires-Dist: requests
Requires-Dist: xmltodict
Provides-Extra: crypto
Requires-Dist: cryptography ; extra == 'crypto'
